odoo/addons/sale_order_action_invoice_create_hook/README.rst
odoo/addons/sale_order_action_invoice_create_hook/__init__.py
odoo/addons/sale_order_action_invoice_create_hook/__manifest__.py
odoo/addons/sale_order_action_invoice_create_hook/hooks.py
odoo/addons/sale_order_action_invoice_create_hook/model/__init__.py
odoo/addons/sale_order_action_invoice_create_hook/model/sale_order.py
odoo/addons/sale_order_action_invoice_create_hook/static/description/icon.png
odoo/addons/sale_order_action_invoice_create_hook/tests/__init__.py
odoo/addons/sale_order_action_invoice_create_hook/tests/test_sale_order_action_create_hook.py
odoo11_addon_sale_order_action_invoice_create_hook-11.0.1.0.0.dist-info/DESCRIPTION.rst
odoo11_addon_sale_order_action_invoice_create_hook-11.0.1.0.0.dist-info/METADATA
odoo11_addon_sale_order_action_invoice_create_hook-11.0.1.0.0.dist-info/RECORD
odoo11_addon_sale_order_action_invoice_create_hook-11.0.1.0.0.dist-info/WHEEL
odoo11_addon_sale_order_action_invoice_create_hook-11.0.1.0.0.dist-info/metadata.json
odoo11_addon_sale_order_action_invoice_create_hook-11.0.1.0.0.dist-info/top_level.txt
